rtl/hello_world.sv
// Simple hello world module for testing cocotb setup
// This module implements a basic counter with enable and reset

module hello_world #(
    parameter WIDTH = 8
) (
    input  logic                clk,
    input  logic                rst_n,
    input  logic                enable,
    output logic [WIDTH-1:0]    counter,
    output logic                overflow
);

    always_ff @(posedge clk or negedge rst_n) begin
        if (!rst_n) begin
            counter <= '0;
            overflow <= 1'b0;
        end else if (enable) begin
            if (counter == (2**WIDTH - 1)) begin
                counter <= '0;
                overflow <= 1'b1;
            end else begin
                counter <= counter + 1;
                overflow <= 1'b0;
            end
        end else begin
            overflow <= 1'b0;
        end
    end

    // Simple assertion for basic functionality
    assert property (@(posedge clk) disable iff (!rst_n)
        enable && (counter == (2**WIDTH - 1)) |=> (counter == 0))
    else $error("Counter overflow behavior incorrect");

endmodule

tests/unit/dump.vcd
$version Generated by VerilatedVcd $end
$timescale 1ps $end
 $scope module  $end
  $var wire 1 # clk $end
  $var wire 1 $ rst_n $end
  $var wire 1 % enable $end
  $var wire 8 & counter [7:0] $end
  $var wire 1 ' overflow $end
  $scope module hello_world $end
   $var wire 32 - WIDTH [31:0] $end
   $var wire 1 ( clk $end
   $var wire 1 ) rst_n $end
   $var wire 1 * enable $end
   $var wire 8 + counter [7:0] $end
   $var wire 1 , overflow $end
  $upscope $end
 $upscope $end
$enddefinitions $end


#0
1#
0$
0%
b00000000 &
0'
1(
0)
0*
b00000000 +
0,
b00000000000000000000000000001000 -
#5000
0#
0(
#10000
1#
1$
1(
1)
#15000
0#
0(
#20000
1#
1(
#20001
0$
0)
#25000
#25001
0#
0(
#30001
1#
1$
1%
1(
1)
1*
#35001
0#
0(
#40001
1#
b00000001 &
1(
b00000001 +
#45001
0#
0(
#50001
1#
b00000010 &
1(
b00000010 +
#55001
0#
0(
#60001
1#
b00000011 &
1(
b00000011 +
#65001
0#
0(
#70001
1#
b00000100 &
1(
b00000100 +
#75001
0#
0(
#80001
1#
b00000101 &
1(
b00000101 +
#85001
0#
0(
#90001
1#
b00000110 &
1(
b00000110 +
#95001
0#
0(
#100001
1#
b00000111 &
1(
b00000111 +
#105001
0#
0(
#110001
1#
b00001000 &
1(
b00001000 +
#115001
0#
0(
#120001
1#
b00001001 &
1(
b00001001 +
#125001
0#
0(
#130001
1#
0%
b00001010 &
1(
0*
b00001010 +
#135001
0#
0(
#140001
1#
1(
#145001
0#
0(
#150001
1#
1(
#155001
0#
0(
#160001
1#
1(
#165001
0#
0(
#170001
1#
1(
#175001
0#
0(
#180001
1#
1(
#185001
0#
0(
#190001
1#
1(
#190002
1%
1*
#195001
#195002
0#
0(
#200002
1#
b00001011 &
1(
b00001011 +
#205002
0#
0(
#210002
1#
b00001100 &
1(
b00001100 +
#215002
0#
0(
#220002
1#
b00001101 &
1(
b00001101 +
#225002
0#
0(
#230002
1#
b00001110 &
1(
b00001110 +
#235002
0#
0(
#240002
1#
b00001111 &
1(
b00001111 +
#245002
0#
0(
#250002
1#
b00010000 &
1(
b00010000 +
#255002
0#
0$
b00000000 &
0(
0)
b00000000 +
#256002
1$
1)
#260002
1#
b00000001 &
1(
b00000001 +
#260003
0$
0%
b00000000 &
0)
0*
b00000000 +
#265002
#265003
0#
0(
#270003
1#
1$
1(
1)
#275003
0#
0(
#280003
1#
1(
#285003
0#
0(
#290003
1#
1(
#295003
0#
0(
#300003
1#
1%
1(
1*
#305003
0#
0(
#310003
1#
0%
b00000001 &
1(
0*
b00000001 +
#315003
0#
0(
#320003
1#
1(
#325003
0#
0(
#330003
1#
1(
#335003
0#
0(
#340003
1#
1(
#345003
0#
0(
#350003
1#
1(
#355003
0#
0(
#360003
1#
1(
#365003
0#
0(
#370003
1#
1%
1(
1*
#375003
0#
0(
#380003
1#
b00000010 &
1(
b00000010 +
#385003
0#
0(
#390003
1#
b00000011 &
1(
b00000011 +
#395003
0#
0(
#400003
1#
b00000100 &
1(
b00000100 +
#405003
0#
0(
#410003
1#
0%
b00000101 &
1(
0*
b00000101 +
#415003
0#
0(
#420003
1#
1(
#425003
0#
0(
#430003
1#
1(
#435003
0#
0(
#440003
1#
1%
1(
1*
#445003
0#
0(
#450003
1#
b00000110 &
1(
b00000110 +
#455003
0#
0(
#460003
1#
0%
b00000111 &
1(
0*
b00000111 +
